markdown_toc_cli/__init__.py
markdown_toc_cli/markdown_toc_cli.py
markdown_toc_cli-0.1.1.dist-info/METADATA
markdown_toc_cli-0.1.1.dist-info/WHEEL
markdown_toc_cli-0.1.1.dist-info/entry_points.txt
markdown_toc_cli-0.1.1.dist-info/top_level.txt
markdown_toc_cli-0.1.1.dist-info/RECORD
