Metadata-Version: 2.1
Name: markdown-toc-cli
Version: 0.1.1
Summary: Generate or insert a table of contents for a Markdown file.
Home-page: https://github.com/noahp/markdown-toc-cli
Author: Noah Pendleton
Author-email: 2538614+noahp@users.noreply.github.com
License: MIT
Platform: UNKNOWN
Classifier: Programming Language :: Python :: 3
Classifier: Programming Language :: Python :: 3 :: Only
Classifier: Programming Language :: Python :: 3.6
Classifier: Programming Language :: Python :: 3.7
Classifier: Programming Language :: Python :: 3.8
Classifier: Programming Language :: Python :: 3.9
Classifier: Programming Language :: Python :: 3.10
Classifier: Programming Language :: Python :: Implementation :: CPython
Requires-Python: >=3.6
Requires-Dist: mistletoe (==0.8.2)
